DataSynthesizer/DataDescriber.py
DataSynthesizer/DataGenerator.py
DataSynthesizer/ModelInspector.py
DataSynthesizer/__init__.py
DataSynthesizer/datatypes/AbstractAttribute.py
DataSynthesizer/datatypes/DateTimeAttribute.py
DataSynthesizer/datatypes/FloatAttribute.py
DataSynthesizer/datatypes/IntegerAttribute.py
DataSynthesizer/datatypes/SocialSecurityNumberAttribute.py
DataSynthesizer/datatypes/StringAttribute.py
DataSynthesizer/datatypes/__init__.py
DataSynthesizer/datatypes/utils/AttributeLoader.py
DataSynthesizer/datatypes/utils/DataType.py
DataSynthesizer/datatypes/utils/__init__.py
DataSynthesizer/lib/PrivBayes.py
DataSynthesizer/lib/__init__.py
DataSynthesizer/lib/utils.py
DataSynthesizer-0.1.13.dist-info/AUTHORS.rst
DataSynthesizer-0.1.13.dist-info/LICENSE
DataSynthesizer-0.1.13.dist-info/METADATA
DataSynthesizer-0.1.13.dist-info/WHEEL
DataSynthesizer-0.1.13.dist-info/top_level.txt
DataSynthesizer-0.1.13.dist-info/RECORD
