Metadata-Version: 2.1
Name: DataSynthesizer
Version: 0.1.13
Summary: Generate synthetic data that simulate a given dataset.
Home-page: https://github.com/DataResponsibly/DataSynthesizer
Author: Data, Responsibly
Author-email: dataresponsibly@gmail.com
License: MIT license
Keywords: DataSynthesizer
Classifier: Development Status :: 2 - Pre-Alpha
Classifier: Intended Audience :: Developers
Classifier: License :: OSI Approved :: MIT License
Classifier: Natural Language :: English
Classifier: Programming Language :: Python :: 3
Classifier: Programming Language :: Python :: 3.7
Requires-Python: >=3.7
License-File: LICENSE
License-File: AUTHORS.rst
Requires-Dist: numpy >=1.18.5
Requires-Dist: pandas >=1.0.5
Requires-Dist: scikit-learn >=0.23.1
Requires-Dist: matplotlib >=3.2.2
Requires-Dist: seaborn >=0.10.1
Requires-Dist: python-dateutil >=2.8.1
